README.md
setup.cfg
setup.py
distributions/Binomialdistribution.py
distributions/Gaussiandistribution.py
distributions/Generaldistribution.py
distributions/__init__.py
gauss_bin_prob.egg-info/PKG-INFO
gauss_bin_prob.egg-info/SOURCES.txt
gauss_bin_prob.egg-info/dependency_links.txt
gauss_bin_prob.egg-info/not-zip-safe
gauss_bin_prob.egg-info/top_level.txt