Metadata-Version: 1.2
Name: gauss-bin-prob
Version: 0.1
Summary: Gaussian and Binomial probability distributions
Home-page: UNKNOWN
Author: github.com/Wakhie
License: UNKNOWN
Platform: UNKNOWN
Requires-Python: >=3
